{"stem":"april","instances":[{"docUri":"calendar\/index.html","score":8,"contexts":[{"form":"April","weight":"1","pos":82,"context":"<mark>April<\/mark> 1, 1909. Thursday","fid":"toc"},{"form":"April","weight":"1","pos":85,"context":"<mark>April<\/mark> 6, 1909. Tuesday","fid":"toc"},{"form":"April","weight":"1","pos":88,"context":"<mark>April<\/mark> 7, 1909. Wednesday","fid":"toc"},{"form":"April","weight":"1","pos":91,"context":"<mark>April<\/mark> 10, 1909. Saturday","fid":"toc"},{"form":"April","weight":"1","pos":95,"context":"<mark>April<\/mark> 11, 1909. Saturday Easter","fid":"toc"},{"form":"April","weight":"1","pos":100,"context":"<mark>April<\/mark> 14, 1909. Wednesday","fid":"toc"},{"form":"April","weight":"1","pos":104,"context":"<mark>April<\/mark> 16, 1909. Friday","fid":"toc"},{"form":"April","weight":"1","pos":108,"context":"<mark>April<\/mark> 18, 1909. Sunday","fid":"toc"}]},{"docUri":"calendarPage.html","score":8,"contexts":[{"form":"April","weight":"1","pos":82,"context":"<mark>April<\/mark> 1, 1909. Thursday","fid":"toc"},{"form":"April","weight":"1","pos":85,"context":"<mark>April<\/mark> 6, 1909. Tuesday","fid":"toc"},{"form":"April","weight":"1","pos":88,"context":"<mark>April<\/mark> 7, 1909. Wednesday","fid":"toc"},{"form":"April","weight":"1","pos":91,"context":"<mark>April<\/mark> 10, 1909. Saturday","fid":"toc"},{"form":"April","weight":"1","pos":95,"context":"<mark>April<\/mark> 11, 1909. Saturday Easter","fid":"toc"},{"form":"April","weight":"1","pos":100,"context":"<mark>April<\/mark> 14, 1909. Wednesday","fid":"toc"},{"form":"April","weight":"1","pos":104,"context":"<mark>April<\/mark> 16, 1909. Friday","fid":"toc"},{"form":"April","weight":"1","pos":108,"context":"<mark>April<\/mark> 18, 1909. Sunday","fid":"toc"}]},{"docUri":"calendar\/e-1909-04-01.html","score":2,"contexts":[{"form":"April","weight":"1","pos":27,"context":" <mark>April<\/mark> 1, 1909. Thursday This is your picture!...","fid":"e-1909-04-01"},{"form":"\"APRIL","weight":"1","pos":45,"context":"...the sticky note there is more text that reads <mark>\"APRIL<\/mark> FOOL!!\" and is underlined.—#lhering","fid":"e-1909-04-01"}]},{"docUri":"calendar\/e-1909-04-06.html","score":1,"contexts":[{"form":"April","weight":"1","pos":46,"context":" <mark>April<\/mark> 6, 1909. Tuesday Theresa makes us every day...","fid":"e-1909-04-06"}]},{"docUri":"calendar\/e-1909-04-07.html","score":1,"contexts":[{"form":"April","weight":"1","pos":22,"context":" <mark>April<\/mark> 7, 1909. Wednesday Ernst wanted a billiard table...","fid":"e-1909-04-07"}]},{"docUri":"calendar\/e-1909-04-10.html","score":1,"contexts":[{"form":"April","weight":"1","pos":17,"context":" <mark>April<\/mark> 10, 1909. Saturday There's a little old...","fid":"e-1909-04-10"}]},{"docUri":"calendar\/e-1909-04-11.html","score":1,"contexts":[{"form":"April","weight":"1","pos":33,"context":" <mark>April<\/mark> 11, 1909. Saturday Easter \"Ah dear but...","fid":"e-1909-04-11"}]},{"docUri":"calendar\/e-1909-04-14.html","score":1,"contexts":[{"form":"April","weight":"1","pos":37,"context":" <mark>April<\/mark> 14, 1909. Wednesday Love from Mary Alicia...","fid":"e-1909-04-14"}]},{"docUri":"calendar\/e-1909-04-16.html","score":1,"contexts":[{"form":"April","weight":"1","pos":10,"context":" <mark>April<\/mark> 16, 1909. Friday fish day This is...","fid":"e-1909-04-16"}]},{"docUri":"calendar\/e-1909-04-18.html","score":1,"contexts":[{"form":"April","weight":"1","pos":8,"context":" <mark>April<\/mark> 18, 1909. Sunday Jewels are all very...","fid":"e-1909-04-18"}]}]}