{"stem":"bank","instances":[{"docUri":"travelLetters\/Brussels-1955-07-26.html","score":3,"contexts":[{"form":"Bank","weight":"3","pos":86,"context":"...in the Bois de Boulougne shopped on the Left <mark>Bank<\/mark>, got train tickets and that night went to...","fid":"brusselsJuly26.xml-n-1"}]},{"docUri":"travelLetters\/Manoir-1955-07.html","score":3,"contexts":[{"form":"banks","weight":"3","pos":217,"context":"...circular 12th Century chapel, or on the <mark>banks<\/mark> of the Loire across from Mme. de Pompadour's...","fid":"Manoir-de-Becheron.xml-n-1"}]}]}