{"stem":"come","instances":[{"docUri":"calendar\/e-1909-03-31.html","score":1,"contexts":[{"form":"coming","weight":"1","pos":54,"context":"...of bed early, and the season of spring <mark>coming<\/mark> early.—#lhering","fid":"e-1909-03-31"}]},{"docUri":"calendar\/e-1909-04-11.html","score":1,"contexts":[{"form":"come","weight":"1","pos":40,"context":"...11, 1909. Saturday Easter \"Ah dear but <mark>come<\/mark> thou back to me Whatever change the years (...","fid":"e-1909-04-11"}]},{"docUri":"calendar\/e-1909-05-01.html","score":1,"contexts":[{"form":"come","weight":"1","pos":17,"context":"...Baskets No one knows who sends them But they <mark>come<\/mark> each first of May Just full of lovely things...","fid":"e-1909-05-01"}]},{"docUri":"calendar\/e-1909-05-06.html","score":1,"contexts":[{"form":"coming","weight":"1","pos":7,"context":"...house with grass around it, as well as smoke <mark>coming<\/mark> out of the chimney—#zmurphy   ","fid":"e-1909-05-06"}]},{"docUri":"travelLetters\/Greenwich-1955-07-18.html","score":1,"contexts":[{"form":"come","weight":"1","pos":74,"context":"...dock just after 10.30 and were not allowed to <mark>come<\/mark> on board. Too bad. Huge ship....","fid":"noon-july.xml-n-1"}]},{"docUri":"warrenLetters\/memorial-pg1.html","score":1,"contexts":[{"form":"come","weight":"1","pos":183,"context":"...Warren Behrend's heroism, with their parents and friends <mark>come<\/mark> today to pay respectful tribute to his wonderful ","fid":"f-."}]},{"docUri":"warrenLetters\/Parents-Letter_1929-12-17-pg1.html","score":1,"contexts":[{"form":"coming","weight":"1","pos":34,"context":"...&amp; offically invite her -and she says she is <mark>coming<\/mark> lawnell 27.?. Possibly You have heard were about...","fid":"f-1929-12-17"}]},{"docUri":"warrenLetters\/Warren-Letter1_1929-12-17-pg3.html","score":1,"contexts":[{"form":"come","weight":"1","pos":56,"context":"...I'm telephoning Betty Brattontonight find out whether she can <mark>come<\/mark> and if so when. If she ","fid":"f-1929-12-17"}]},{"docUri":"warrenLetters\/Warren-Letter1_1929-12-17-pg4.html","score":1,"contexts":[{"form":"come","weight":"1","pos":11,"context":" can <mark>come<\/mark> you will have received a telegram from me before...","fid":"f-1929-12-17"}]}]}