{"stem":"danish","instances":[{"docUri":"travelLetters\/Copenhagen-1955-07-28.html","score":1,"contexts":[{"form":"Danish","weight":"1","pos":166,"context":"...lived a long time in Texas. Does notnSpeak <mark>Danish<\/mark>. After meeting them all Mr Dessau Asked us...","fid":"july28.xml-n-2"}]},{"docUri":"travelLetters\/Copenhagen-1955-07-29.html","score":1,"contexts":[{"form":"danish","weight":"1","pos":176,"context":"...day- to bournhiolm , the <mark>danish<\/mark> Island. An air plane to get there! ","fid":"july29.xml-n-1"}]}]}