{"stem":"dark","instances":[{"docUri":"calendar\/e-1909-02-17.html","score":9,"contexts":[{"form":"dark","weight":"3","pos":8,"context":" Each morning very early When all is <mark>dark<\/mark> and still Ernst goes off in inky blackness To...","fid":"e-1909-02-17"},{"form":"dark","weight":"3","pos":22,"context":"...think he's very good to get up when it’s <mark>dark<\/mark> For tho’ he says he doesn’t mind It can't...","fid":"e-1909-02-17"},{"form":"dark","weight":"3","pos":32,"context":"Poor thing! is it still <mark>dark<\/mark> when you arise?","fid":"e-1909-02-17"}]},{"docUri":"calendar\/e-1909-01-30.html","score":3,"contexts":[{"form":"dark","weight":"3","pos":17,"context":"...clock gives me a shock Each morning when it’s <mark>dark<\/mark> It likes the fun, but I’ve begun To...","fid":"e-1909-01-30"}]}]}