{"stem":"kind","instances":[{"docUri":"calendar\/e-1909-06-19.html","score":1,"contexts":[{"form":"kind","weight":"1","pos":192,"context":"...waiting? Did they have a housekeeper of some <mark>kind<\/mark>? I have so many questions. —#rgerzevske...","fid":"e-1909-06-19"}]},{"docUri":"siple\/1935-12-09.html","score":1,"contexts":[{"form":"kindly","weight":"1","pos":129,"context":" The sextant you so <mark>kindly<\/mark> loaned us helped to guideus through the hundreds of...","fid":"f-1935-12-09"}]},{"docUri":"sipleLettersPage.html","score":1,"contexts":[{"form":"kindly","weight":"1","pos":129,"context":" The sextant you so <mark>kindly<\/mark> loaned us helped to guideus through the hundreds of...","fid":"f-1935-12-09"}]},{"docUri":"travelLetters\/Copenhagen-1955-07-28.html","score":1,"contexts":[{"form":"kind","weight":"1","pos":225,"context":"...we LIKE the Toborg beer better than ant other <mark>kind<\/mark>!! ","fid":"july28.xml-n-2"}]}]}