{"stem":"might","instances":[{"docUri":"calendar\/e-1909-04-11.html","score":1,"contexts":[{"form":"might","weight":"1","pos":207,"context":"The flowers in the drawing <mark>might<\/mark> be chrysanthemums or minnow daffodils based on their color...","fid":"e-1909-04-11"}]},{"docUri":"warrenLetters\/Warren-Letter1_1929-12-17-pg2.html","score":1,"contexts":[{"form":"might","weight":"1","pos":153,"context":"...night.Miss Black- stone said that brothers <mark>might<\/mark> get through the portals to see their sisters....","fid":"f-1929-12-17"}]},{"docUri":"warrenLetters\/Warren-Letters2_1929-12-19-pg3.html","score":1,"contexts":[{"form":"might","weight":"1","pos":151,"context":"...has no definite plans for next summer Christmas and <mark>might<\/mark> be able to go I'll ask her if for...","fid":"f-1929-12-19"}]}]}