{"stem":"unselfish","instances":[{"docUri":"warrenLetters\/memorial-pg1.html","score":9,"contexts":[{"form":"unselfish","weight":"3","pos":107,"context":"...dedicate ourselves to the call of duty and of <mark>unselfish<\/mark> service. This deed should, and I confidently trust...","fid":"f-."},{"form":"unselfish","weight":"3","pos":130,"context":"...look out into the world today the call to <mark>unselfish<\/mark> service was never so compelling. Many of the...","fid":"f-."},{"form":"unselfish","weight":"3","pos":151,"context":"...words of kindess, of self forgetfulness, and <mark>unselfish<\/mark> sacrifice. May we not treasure Warren's heroic deed...","fid":"f-."}]}]}