{"stem":"earli","instances":[{"docUri":"pages\/readingView.html","score":7,"contexts":[{"form":"early","weight":"2","pos":180,"context":"...February 17, 1909. Wednesday Each morning very <mark>early<\/mark> When all is dark and still Earnest goes off...","fid":"e-1909-02-17","in":["ssCtx5"]},{"form":"early","weight":"2","pos":419,"context":"...March 31, 1909. Wednesday 4.30 AM. \"An <mark>early<\/mark> spring.\" This is you springing out of bed...","fid":"e-1909-03-31","in":["ssCtx5"]},{"form":"early","weight":"1","pos":435,"context":"...once again uses a pun. She says \"an <mark>early<\/mark> spring\". This both referenceing the person in the...","fid":"e-1909-03-31"},{"form":"early","weight":"1","pos":442,"context":"...the person in the image getting out of bed <mark>early<\/mark>, and the season of spring coming early.—#...","fid":"e-1909-03-31"},{"form":"early","weight":"1","pos":446,"context":"...bed early, and the season of spring coming <mark>early<\/mark>.—#lhering","fid":"e-1909-03-31"}]}]}