{"stem":"german","instances":[{"docUri":"pages\/readingView.html","score":10,"contexts":[{"form":"german","weight":"2","pos":1111,"context":"...Drawing of a small grey dog that is drinking <mark>german<\/mark> beer with water underneath the dogs feet.—#zmurphy...","fid":"e-1909-05-22"},{"form":"german","weight":"2","pos":1128,"context":".... Reichemheims dog is queer He likes that nasty <mark>german<\/mark> beer. Here he is lapping it up -...","fid":"e-1909-05-22","in":["ssCtx5"]},{"form":"german","weight":"2","pos":1154,"context":"...Drawing of a small grey dog that is drinking <mark>german<\/mark> beer with water underneath the dogs feet.—#zmurphy...","fid":"e-1909-06-09"},{"form":"german","weight":"2","pos":1171,"context":".... Reichemheims dog is queer He likes that nasty <mark>german<\/mark> beer. Here he is lapping it up -...","fid":"e-1909-06-09","in":["ssCtx5"]},{"form":"german","weight":"1","pos":1140,"context":"...very unhappy at Mr. Reichemheims dog for liking <mark>german<\/mark> beer and expresses that it is really bad for...","fid":"e-1909-05-22"},{"form":"german","weight":"1","pos":1183,"context":"...very unhappy at Mr. Reichemheims dog for liking <mark>german<\/mark> beer and expresses that it is really bad for...","fid":"e-1909-06-09"}]}]}