{"stem":"larg","instances":[{"docUri":"pages\/readingView.html","score":10,"contexts":[{"form":"large","weight":"2","pos":158,"context":"  Mr Behrend holding a <mark>large<\/mark> bug. —#acolemanreeves   ","fid":"e-1909-02-16"},{"form":"large","weight":"2","pos":208,"context":" A <mark>large<\/mark> question mark in the center of the paper.—#...","fid":"e-1909-03-08"},{"form":"large","weight":"2","pos":1272,"context":"...articles, with one containing a drawing of a <mark>large<\/mark> woman and a small man with some text underneath...","fid":"e-1909-06-16"},{"form":"large","weight":"2","pos":1291,"context":"...1909. Wednesday In case a woman is so <mark>large<\/mark> around the waist That her husband can't hug her...","fid":"e-1909-06-16","in":["ssCtx5"]},{"form":"large","weight":"2","pos":1312,"context":"...time going round. I hope I won't be <mark>large<\/mark> again Care of the Hands in Winter Floreance....","fid":"e-1909-06-16","in":["ssCtx5"]}]}]}